gdal2mbtiles/__init__.py
gdal2mbtiles/constants.py
gdal2mbtiles/default_rgba.png
gdal2mbtiles/exceptions.py
gdal2mbtiles/gd_types.py
gdal2mbtiles/gdal.py
gdal2mbtiles/helpers.py
gdal2mbtiles/main.py
gdal2mbtiles/mbtiles.py
gdal2mbtiles/renderers.py
gdal2mbtiles/storages.py
gdal2mbtiles/utils.py
gdal2mbtiles/vips.py
gdal2mbtiles-2.1.5.dist-info/LICENSE
gdal2mbtiles-2.1.5.dist-info/METADATA
gdal2mbtiles-2.1.5.dist-info/NOTICE
gdal2mbtiles-2.1.5.dist-info/WHEEL
gdal2mbtiles-2.1.5.dist-info/entry_points.txt
gdal2mbtiles-2.1.5.dist-info/top_level.txt
gdal2mbtiles-2.1.5.dist-info/zip-safe
gdal2mbtiles-2.1.5.dist-info/RECORD
