Metadata-Version: 2.1
Name: gdal2mbtiles
Version: 2.1.5
Summary: Converts a GDAL-readable dataset into an MBTiles file.This is used to generate web maps.
Home-page: https://github.com/ecometrica/gdal2mbtiles
Author: Ecometrica
Author-email: software@ecometrica.com
License: Apache Software License, version 2.0
Classifier: Development Status :: 5 - Production/Stable
Classifier: Environment :: Console
Classifier: Intended Audience :: Other Audience
Classifier: License :: OSI Approved :: Apache Software License
Classifier: Operating System :: POSIX
Classifier: Programming Language :: Python :: 3.6
Classifier: Programming Language :: Python :: 3.7
Classifier: Programming Language :: Python :: 3.8
Classifier: Topic :: Multimedia :: Graphics :: Graphics Conversion
Classifier: Topic :: Scientific/Engineering :: GIS
License-File: LICENSE
License-File: NOTICE
Requires-Dist: future
Requires-Dist: numexpr
Requires-Dist: numpy
Requires-Dist: pyvips
Requires-Dist: webcolors
Provides-Extra: tests
Requires-Dist: pytest ; extra == 'tests'
Requires-Dist: pytest-pythonpath ; extra == 'tests'
Requires-Dist: distro ; (platform_system == "Linux") and extra == 'tests'
